ibires/.DS_Store
ibires/__init__.py
ibires/codes.py
ibires/core.py
ibires/reports.py
ibires/simulate.py
ibires/hsi/1.json
ibires/hsi/1.py
ibires/hsi/2.json
ibires/hsi/2.py
ibires/hsi/Makefile
ibires/hsi/hsi1.json
ibires/hsi/hsi2.json
ibires/hsi/merge.py
ibires/hsi/merged.json
ibires/test/__init__.py
ibires/test/core_test.py
ibires/test/example2_test.py
ibires/test/example_test.py
ibires/test/reports_test.py
ibires/test/simulate_test.py
ibires-0.2.2.dist-info/DESCRIPTION.rst
ibires-0.2.2.dist-info/METADATA
ibires-0.2.2.dist-info/RECORD
ibires-0.2.2.dist-info/WHEEL
ibires-0.2.2.dist-info/metadata.json
ibires-0.2.2.dist-info/top_level.txt
