Metadata-Version: 2.0
Name: ibires
Version: 0.2.2
Summary: UNKNOWN
Home-page: https://bitbucket.org/hyllos/ibires
Author: Benjamin Weber
Author-email: UNKNOWN
License: MIT
Platform: UNKNOWN
Classifier: Intended Audience :: Telecommunications Industry
Classifier: Intended Audience :: Information Technology
Classifier: Intended Audience :: Developers
Classifier: Operating System :: OS Independent
Classifier: Programming Language :: Python :: 3
Classifier: Development Status :: 4 - Beta
Requires-Dist: arrow
Requires-Dist: pytest
Requires-Dist: requests (>=2.0)
Requires-Dist: responses
